router_fifo.v
`timescale 1ns/1ps

module fifo(
    input clk,rst_n,soft_rst,
    input rd_en,wr_en,
    input [7:0]data_in,
    input lfd_state,
    output reg [7:0]data_out,
    output empty,full
);
reg [8:0]mem[0:15];
 reg [6:0]counter;
 reg [4:0]rd_ptr,wr_ptr;
integer i;
//-----------------------------------------------------------------------------
//
always@(posedge clk)
begin 
if(rst_n)
    counter<=7'b0;
else if(soft_rst)
    counter<=7'b0;
else if(rd_en && !empty)  
     if(mem[rd_ptr[3:0]][8]==1'b1)
counter <= mem[rd_ptr[3:0]][7:2];
     else if(counter != 0)
     counter<=counter-1;
end 
//------------------------------------------------------------------------------

assign full=(wr_ptr  == {!rd_ptr[4],rd_ptr[3:0]});   //Full logic 
assign empty=(rd_ptr==wr_ptr);                       //empty logic 

//-------------------------------------------------------------------------------
//Read logic 

always@(posedge clk)
begin
    if(!rst_n)
    begin 
    data_out<=0;
    rd_ptr<=0;
    end 
    else if(soft_rst)
    begin 
    data_out<=8'hz;;
     rd_ptr<=0;
    end 
    
    else if(rd_en && !empty)
    begin
        data_out<=mem[rd_ptr[3:0]];
        rd_ptr<=rd_ptr+1;
    end  
    else if(counter==0 && data_out!=0 )
    data_out<=8'hz;
end 

//----------------------------------------------------------------------------------
//Write logic 
always@(posedge clk)
begin
    if(!rst_n)
    begin
        wr_ptr<=0;
        for(i=0;i<16;i=i+1)
        mem[i] <= 0; 
    end  
    else if(soft_rst)
    begin
         wr_ptr<=0;
            for(i=0;i<16;i=i+1)
        mem[i] <= 0; 
    end 
    else if (wr_en && !full)
    begin 
    mem[wr_ptr[3:0]] <= {lfd_state,data_in};
    wr_ptr<=wr_ptr+1;
    end 
end 
    endmodule

FIFO_tb.v
`timescale 1ns/1ps

module fifo_tb;

reg clk;
reg rst_n;
reg soft_rst;
reg rd_en;
reg wr_en;
reg lfd_state;
reg [7:0] data_in;

wire [7:0] data_out;
wire full;
wire empty;

fifo DUT (
    .clk(clk),
    .rst_n(rst_n),
    .soft_rst(soft_rst),
    .rd_en(rd_en),
    .wr_en(wr_en),
    .data_in(data_in),
    .lfd_state(lfd_state),
    .data_out(data_out),
    .empty(empty),
    .full(full)
);


//---------------------------------------------------
// Clock Generation
//---------------------------------------------------

initial
begin
    clk = 0;
    forever #5 clk = ~clk;
end


//---------------------------------------------------
// Random Packet Write Task
//---------------------------------------------------

task write_packet;

integer payload_len;
integer i;

begin

    payload_len = $urandom_range(1,10);

    // Header
    @(posedge clk);

    wr_en     = 1;
    lfd_state = 1;

    data_in = {payload_len[5:0],2'b01};

    $display("\nHEADER WRITTEN = %h Payload Length=%0d",
              data_in,payload_len);

    //------------------------------------------------
    // Payload
    //------------------------------------------------

    for(i=0;i<payload_len;i=i+1)
    begin
        @(posedge clk);

        lfd_state = 0;
        data_in   = $random;

        $display("Payload[%0d] = %h",
                  i,data_in);
    end

    //------------------------------------------------
    // Parity
    //------------------------------------------------

    @(posedge clk);

    data_in = $random;

    $display("Parity = %h",data_in);

    @(posedge clk);

    wr_en = 0;

end
endtask


//---------------------------------------------------
// Read Packet Task
//---------------------------------------------------

task read_fifo(
    input a,
    input [8:0]b
);
begin 
 a=rd_en;
 b=data_out;
 #10;
end 
integer i;

begin

    rd_en = 1;

    for(i=0;i<20;i=i+1)
    begin
        @(posedge clk);

        $display("Time=%0t DATA_OUT=%h EMPTY=%b FULL=%b COUNTER=%0d",
        $time,
        data_out,
        empty,
        full,
        DUT.counter);

        if(empty)
            disable read_fifo;
    end

    rd_en = 0;

end
endtask


//---------------------------------------------------
// Monitor
//---------------------------------------------------

initial
begin
    $monitor(
    "T=%0t WR_PTR=%0d RD_PTR=%0d FULL=%b EMPTY=%b CNT=%0d DATA_OUT=%h",
    $time,
    DUT.wr_ptr,
    DUT.rd_ptr,
    full,
    empty,
    DUT.counter,
    data_out);
end


//---------------------------------------------------
// Stimulus
//---------------------------------------------------

initial
begin

    rst_n     = 0;
    soft_rst  = 0;
    rd_en     = 0;
    wr_en     = 0;
    lfd_state = 0;
    data_in   = 0;

    //------------------------------------------------
    // Reset
    //------------------------------------------------

    #20;
    rst_n = 1;

    //------------------------------------------------
    // Write 3 random packets
    //------------------------------------------------

    repeat(3)
        write_packet();

    //------------------------------------------------
    // Read everything
    //------------------------------------------------

    #20;
    read_fifo();

    //------------------------------------------------
    // Fill FIFO completely
    //------------------------------------------------

    $display("\n========== FILL FIFO ==========");

    wr_en = 1;
    lfd_state = 0;

    repeat(20)
    begin
        @(posedge clk);
        data_in = $random;
    end

    wr_en = 0;

    #50;

    //------------------------------------------------
    // Soft Reset
    //------------------------------------------------

    $display("\n========== SOFT RESET ==========");

    soft_rst = 1;
    @(posedge clk);
    soft_rst = 0;

    #50;

    //------------------------------------------------
    // Simultaneous Read Write
    //------------------------------------------------

    $display("\n========== READ + WRITE ==========");

    fork

        begin
            repeat(10)
            begin
                @(posedge clk);
                wr_en = 1;
                data_in = $random;
            end
            wr_en = 0;
        end

        begin
            repeat(10)
            begin
                @(posedge clk);
                rd_en = 1;
            end
            rd_en = 0;
        end

    join

    #100;

    $finish;

end
initial 
begin
    $monitor("Time=%0t rst_n=%b soft_rst=%b rd_en=%b wr_en=%b data_in=%b data_out=%b",
     $time,rst_n,soft_rst,rd_en,wr_en,data_in,data_out); 
end 

//---------------------------------------------------
// Dump File
//---------------------------------------------------

initial
begin
    $dumpfile("fifo.vcd");
    $dumpvars(0,fifo_tb);
end

endmodule

fifo.vcd
$date
	Tue Jun 23 13:57:50 2026
$end
$version
	Icarus Verilog
$end
$timescale
	1ps
$end
$scope module fifo_tb $end
$var wire 1 ! full $end
$var wire 1 " empty $end
$var wire 8 # data_out [7:0] $end
$var reg 1 $ clk $end
$var reg 8 % data_in [7:0] $end
$var reg 1 & lfd_state $end
$var reg 1 ' rd_en $end
$var reg 1 ( rst_n $end
$var reg 1 ) soft_rst $end
$var reg 1 * wr_en $end
$scope module DUT $end
$var wire 1 $ clk $end
$var wire 8 + data_in [7:0] $end
$var wire 1 & lfd_state $end
$var wire 1 ' rd_en $end
$var wire 1 ( rst_n $end
$var wire 1 ) soft_rst $end
$var wire 1 * wr_en $end
$var wire 1 ! full $end
$var wire 1 " empty $end
$var reg 7 , counter [6:0] $end
$var reg 8 - data_out [7:0] $end
$var reg 5 . rd_ptr [4:0] $end
$var reg 5 / wr_ptr [4:0] $end
$var integer 32 0 i [31:0] $end
$upscope $end
$scope task read_fifo $end
$var integer 32 1 i [31:0] $end
$upscope $end
$scope task write_packet $end
$var integer 32 2 i [31:0] $end
$var integer 32 3 payload_len [31:0] $end
$upscope $end
$upscope $end
$enddefinitions $end
#0
$dumpvars
bx 3
bx 2
bx 1
bx 0
bx /
bx .
bx -
bx ,
b0 +
0*
0)
0(
0'
0&
b0 %
0$
bx #
x"
x!
$end
#5000
0!
1"
b0 .
b0 #
b0 -
b0 /
b10000 0
1$
#10000
0$
#15000
b10000 0
1$
#20000
0$
b110 3
1(
#25000
b0 ,
0"
b1 /
b0 2
b11001 %
b11001 +
1&
1*
1$
#30000
0$
#35000
b10 /
b1 2
b100100 %
b100100 +
0&
1$
#40000
0$
#45000
b11 /
b10 2
b10000001 %
b10000001 +
1$
#50000
0$
#55000
b100 /
b11 2
b1001 %
b1001 +
1$
#60000
0$
#65000
b101 /
b100 2
b1100011 %
b1100011 +
1$
#70000
0$
#75000
b110 /
b101 2
b1101 %
b1101 +
1$
#80000
0$
#85000
b111 /
b110 2
b10001101 %
b10001101 +
1$
#90000
0$
#95000
b1000 /
b1100101 %
b1100101 +
1$
#100000
0$
#105000
b11 3
0*
1$
#110000
0$
#115000
b1001 /
b0 2
b1101 %
b1101 +
1&
1*
1$
#120000
0$
#125000
b1010 /
b1 2
b10010 %
b10010 +
0&
1$
#130000
0$
#135000
b1011 /
b10 2
b1 %
b1 +
1$
#140000
0$
#145000
b1100 /
b11 2
b1101 %
b1101 +
1$
#150000
0$
#155000
b1101 /
b1110110 %
b1110110 +
1$
#160000
0$
#165000
b1110 /
b1 3
0*
1$
#170000
0$
#175000
b1111 /
b0 2
b101 %
b101 +
1&
1*
1$
#180000
0$
#185000
1!
b10000 /
b1 2
b111101 %
b111101 +
0&
1$
#190000
0$
#195000
b11101101 %
b11101101 +
1$
#200000
0$
#205000
0*
1$
#210000
0$
#215000
1$
#220000
0$
#225000
0!
b1 .
b11001 #
b11001 -
1$
b1 1
1'
#230000
0$
#235000
b10 .
b10 1
1$
#240000
0$
#245000
b11 .
b10000001 #
b10000001 -
b11 1
1$
#250000
0$
#255000
b100 .
b100 1
1$
#260000
0$
#265000
b101 .
b1100011 #
b1100011 -
b101 1
1$
#270000
0$
#275000
b110 .
b110 1
1$
#280000
0$
#285000
b111 .
b10001101 #
b10001101 -
b111 1
1$
#290000
0$
#295000
b1000 .
b1000 1
1$
#300000
0$
#305000
b1001 .
b1101 #
b1101 -
b1001 1
1$
#310000
0$
#315000
b1010 .
b1010 1
1$
#320000
0$
#325000
b1011 .
b1 #
b1 -
b1011 1
1$
#330000
0$
#335000
b1100 .
b1100 1
1$
#340000
0$
#345000
b1101 .
b1110110 #
b1110110 -
b1101 1
1$
#350000
0$
#355000
b1110 .
b1110 1
1$
#360000
0$
#365000
b1111 .
b101 #
b101 -
b1111 1
1$
#370000
0$
#375000
0!
1"
b10000 .
b10000 1
1$
#380000
0$
#385000
bz #
bz -
1*
1$
#390000
0$
#395000
0"
b10001 /
b10001100 %
b10001100 +
1$
#400000
0$
#405000
b10001 .
b10001100 #
b10001100 -
b10010 /
b11111001 %
b11111001 +
1$
#410000
0$
#415000
b10011 /
0"
b10010 .
b11000110 %
b11000110 +
1$
#420000
0$
#425000
b10011 .
b11000110 #
b11000110 -
b10100 /
b11000101 %
b11000101 +
1$
#430000
0$
#435000
b10101 /
0"
b10100 .
b10101010 %
b10101010 +
1$
#440000
0$
#445000
b10101 .
b10101010 #
b10101010 -
b10110 /
b11100101 %
b11100101 +
1$
#450000
0$
#455000
b10111 /
0"
b10110 .
b1110111 %
b1110111 +
1$
#460000
0$
#465000
b10111 .
b1110111 #
b1110111 -
b11000 /
b10010 %
b10010 +
1$
#470000
0$
#475000
b11001 /
0"
b11000 .
b10001111 %
b10001111 +
1$
#480000
0$
#485000
b11001 .
b10001111 #
b10001111 -
b11010 /
b11110010 %
b11110010 +
1$
#490000
0$
#495000
b11011 /
0"
b11010 .
b11001110 %
b11001110 +
1$
#500000
0$
#505000
b11011 .
b11001110 #
b11001110 -
b11100 /
b11101000 %
b11101000 +
1$
#510000
0$
#515000
b11101 /
0"
b11100 .
b11000101 %
b11000101 +
1$
#520000
0$
#525000
b11101 .
b11000101 #
b11000101 -
b11110 /
b1011100 %
b1011100 +
1$
#530000
0$
#535000
b11111 /
0"
b11110 .
b10111101 %
b10111101 +
1$
#540000
0$
#545000
b11111 .
b10111101 #
b10111101 -
b0 /
b101101 %
b101101 +
1$
#550000
0$
#555000
b1 /
0"
b0 .
b1100101 %
b1100101 +
1$
#560000
0$
#565000
b1 .
b1100101 #
b1100101 -
b10 /
b1100011 %
b1100011 +
1$
#570000
0$
#575000
b11 /
0"
b10 .
b1010 %
b1010 +
1$
#580000
0$
#585000
b11 .
b1010 #
b1010 -
b100 /
0*
b10000000 %
b10000000 +
1$
#590000
0$
#595000
1"
b100 .
1$
#600000
0$
#605000
bz #
bz -
1$
#610000
0$
#615000
1$
#620000
0$
#625000
1$
#630000
0$
#635000
1$
0)
#640000
0$
#645000
1$
#650000
0$
#655000
1$
#660000
0$
#665000
1$
#670000
0$
#675000
1$
#680000
0$
#685000
0"
b101 /
b100000 %
b100000 +
1*
1$
#690000
0$
#695000
b110 /
0"
b101 .
b100000 #
b100000 -
b10101010 %
b10101010 +
1$
#700000
0$
#705000
b110 .
b111 /
b10011101 %
b10011101 +
1$
#710000
0$
#715000
b1000 /
0"
b111 .
b10011101 #
b10011101 -
b10010110 %
b10010110 +
1$
#720000
0$
#725000
b1000 .
b1001 /
b10011 %
b10011 +
1$
#730000
0$
#735000
b1010 /
0"
b1001 .
b10011 #
b10011 -
b1101 %
b1101 +
1$
#740000
0$
#745000
b1010 .
b1011 /
b1010011 %
b1010011 +
1$
#750000
0$
#755000
b1100 /
0"
b1011 .
b1010011 #
b1010011 -
b1101011 %
b1101011 +
1$
#760000
0$
#765000
b1100 .
b1101 /
b11010101 %
b11010101 +
1$
#770000
0$
#775000
b1110 /
0"
b1101 .
b11010101 #
b11010101 -
0*
b10 %
b10 +
0'
1$
#780000
0$
#785000
bz #
bz -
1$
