router_fsm.v

	module router_fsm(
  input clk,rst_n,
  input pkt_valid,
  input parity_done,
  input [1:0]data_in,
  input soft_rst_0,
  input soft_rst_1,
  input soft_rst_2,
  input fifo_full,
  input fifo_empty_0,
  input fifo_empty_1,
  input fifo_empty_2,
  
  output low_pkt_valid,
  output detect_add,
  output busy,
  output ld_state,
  output laf_state,
  output full_state,
  output write_en_reg,
  output rst_int_reg,
  output lfd_state
);
parameter  DECODE_ADDRESS=3'b000 ; 
parameter  LOAD_FIRST_DATA = 3'b001 ;
parameter  LOAD_DATA = 3'b010 ;
parameter  WAIT_TILL_EMPTY = 3'b011 ;
parameter  FIFO_FULL_STATE = 3'b100;
parameter  LOAD_PARITY = 3'b101;
parameter  CHECK_PARITY_ERROR = 3'b110;
parameter  LOAD_AFTER_FULL = 3'b111;


reg [2:0] state,next_state;
reg [1:0] addr;          //Temp reg to store address 


//Present state sequential logic  -- Middle block 

always@(posedge clk)
begin 
  addr=data_in; 
  if(!rst_n)
    state <= DECODE_ADDRESS;
  else if(soft_rst_0 || soft_rst_1 || soft_rst_2)
    state <= DECODE_ADDRESS;
  else
    state<=next_state;
end

// Next state combinational logic 
always@(*)
begin

 next_state = DECODE_ADDRESS;
 case(state)
 DECODE_ADDRESS:begin            //DECODE_ADDRESS

  

  if((pkt_valid && (data_in[1:0]==2'b00) && fifo_empty_0) ||
   (pkt_valid && (data_in[1:0]==2'b01) && fifo_empty_1) ||
   (pkt_valid && (data_in[1:0]==2'b10) && fifo_empty_2))
	
       next_state=LOAD_FIRST_DATA;

  else if((pkt_valid & (data_in[1:0] == 2'b00) & !fifo_empty_0)||
  (pkt_valid & (data_in[1:0] == 2'b01) & !fifo_empty_1)||
  (pkt_valid & (data_in[1:0] == 2'b10) & !fifo_empty_2) )

       next_state = WAIT_TILL_EMPTY;

   else 
      next_state = DECODE_ADDRESS;     

end 
 LOAD_FIRST_DATA:begin             //LOAD_FIRST_DATA
  next_state = LOAD_DATA;
 end 

 LOAD_DATA:begin                  // LOAD DATA
  if(fifo_full)
  next_state = FIFO_FULL_STATE; 

  else if(!fifo_full && !pkt_valid)
   next_state = LOAD_PARITY;
   else 
   next_state = LOAD_DATA;
 end 

 WAIT_TILL_EMPTY:begin            // WAIT_TILL_EMPTY
  if((fifo_empty_0 && (addr == 0)) || (fifo_empty_1 && (addr == 1)) ||
  (fifo_empty_2 && (addr == 2)))

       next_state = LOAD_FIRST_DATA;

  else 
 next_state = WAIT_TILL_EMPTY;
 end 

 FIFO_FULL_STATE:begin                //FIFO_FULL_STATE
  if(fifo_full)
  next_state = FIFO_FULL_STATE;
  else  // !fifo_full
  next_state = LOAD_AFTER_FULL;
 end 

 LOAD_PARITY: begin
 next_state = CHECK_PARITY_ERROR ;     //LOAD_PARITY
 
end 
 CHECK_PARITY_ERROR:begin                // CHECK_PARITY_ERROR
  if(!fifo_full)
  next_state = DECODE_ADDRESS;
  else 
  next_state = FIFO_FULL_STATE;

 end 

 LOAD_AFTER_FULL:begin               //LOAD_AFTER_FULL

   if(parity_done)
      next_state = DECODE_ADDRESS;
  else if(!parity_done && !low_pkt_valid)
      next_state = LOAD_DATA;
  else if(!parity_done && low_pkt_valid)
      next_state = LOAD_PARITY;
 end 
 endcase 
end 

// Output logic -- combinational 
assign detect_add = (state == DECODE_ADDRESS);

assign lfd_state = (state == LOAD_FIRST_DATA);

assign  busy = (state == LOAD_FIRST_DATA) || (state == LOAD_PARITY)||
(state == LOAD_AFTER_FULL)||(state == FIFO_FULL_STATE)||(state == LOAD_AFTER_FULL)
|| (state == WAIT_TILL_EMPTY)||(state == CHECK_PARITY_ERROR);

assign ld_state = (state == LOAD_DATA);

assign write_en_reg = (state == LOAD_DATA) || (state == LOAD_PARITY)||
(state == LOAD_AFTER_FULL);

assign full_state = ( state == FIFO_FULL_STATE);

assign laf_state = (state == LOAD_AFTER_FULL);

assign low_pkt_valid = (state == LOAD_AFTER_FULL);

assign rst_int_reg = (state == CHECK_PARITY_ERROR);

endmodule

router_fsm_tb.v
`timescale 1ns/1ps

module tb_router_fsm;

reg clk;
reg rst_n;

reg pkt_valid;
reg parity_done;
reg [1:0] data_in;

reg soft_rst_0;
reg soft_rst_1;
reg soft_rst_2;

reg fifo_full;
reg fifo_empty_0;
reg fifo_empty_1;
reg fifo_empty_2;

wire low_pkt_valid;
wire detect_add;
wire busy;
wire ld_state;
wire laf_state;
wire full_state;
wire write_en_reg;
wire rst_int_reg;
wire lfd_state;

// DUT

router_fsm DUT(
.clk(clk),
.rst_n(rst_n),
.pkt_valid(pkt_valid),
.parity_done(parity_done),
.data_in(data_in),
.soft_rst_0(soft_rst_0),
.soft_rst_1(soft_rst_1),
.soft_rst_2(soft_rst_2),
.fifo_full(fifo_full),
.fifo_empty_0(fifo_empty_0),
.fifo_empty_1(fifo_empty_1),
.fifo_empty_2(fifo_empty_2),

.low_pkt_valid(low_pkt_valid),
.detect_add(detect_add),
.busy(busy),
.ld_state(ld_state),
.laf_state(laf_state),
.full_state(full_state),
.write_en_reg(write_en_reg),
.rst_int_reg(rst_int_reg),
.lfd_state(lfd_state)
);

/////////////////////////////////////////////////////////
// Clock
/////////////////////////////////////////////////////////

initial
begin
 clk = 0;
 forever #5 clk = ~clk;
end

/////////////////////////////////////////////////////////
// Monitor
/////////////////////////////////////////////////////////

initial
begin
 $monitor(
 "T=%0t State=%0d Next=%0d pkt_valid=%b fifo_full=%b detect=%b lfd=%b ld=%b laf=%b full=%b busy=%b",
 $time,
 DUT.state,
 DUT.next_state,
 pkt_valid,
 fifo_full,
 detect_add,
 lfd_state,
 ld_state,
 laf_state,
 full_state,
 busy
 );
end

/////////////////////////////////////////////////////////
// Stimulus
/////////////////////////////////////////////////////////

initial
begin

//------------------------------------------------------
// Initial Values
//------------------------------------------------------

rst_n = 0;

pkt_valid = 0;
parity_done = 0;

data_in = 2'b00;

fifo_full = 0;

fifo_empty_0 = 1;
fifo_empty_1 = 1;
fifo_empty_2 = 1;

soft_rst_0 = 0;
soft_rst_1 = 0;
soft_rst_2 = 0;

#20;
rst_n = 1;

/////////////////////////////////////////////////////////
// TEST-1
// Normal Packet Flow
//
// DECODE_ADDRESS
// LOAD_FIRST_DATA
// LOAD_DATA
// LOAD_PARITY
// CHECK_PARITY_ERROR
// DECODE_ADDRESS
/////////////////////////////////////////////////////////

$display("\nTEST1 NORMAL FLOW");

data_in = 2'b00;
pkt_valid = 1;

#20;

pkt_valid = 0;

#30;

/////////////////////////////////////////////////////////
// TEST-2
// WAIT_TILL_EMPTY
/////////////////////////////////////////////////////////

$display("\nTEST2 WAIT_TILL_EMPTY");

data_in = 2'b01;

fifo_empty_1 = 0;

pkt_valid = 1;

#20;

fifo_empty_1 = 1;

#20;

pkt_valid = 0;

#20;

/////////////////////////////////////////////////////////
// TEST-3
// FIFO_FULL_STATE
/////////////////////////////////////////////////////////

$display("\nTEST3 FIFO FULL");

data_in = 2'b10;

fifo_empty_2 = 1;

pkt_valid = 1;

#20;

fifo_full = 1;

#30;

fifo_full = 0;

#20;

/////////////////////////////////////////////////////////
// TEST-4
// LOAD_AFTER_FULL -> LOAD_DATA
/////////////////////////////////////////////////////////

$display("\nTEST4 LOAD_AFTER_FULL TO LOAD_DATA");

parity_done = 0;

force DUT.low_pkt_valid = 0;

#20;

release DUT.low_pkt_valid;

/////////////////////////////////////////////////////////
// TEST-5
// LOAD_AFTER_FULL -> LOAD_PARITY
/////////////////////////////////////////////////////////

$display("\nTEST5 LOAD_AFTER_FULL TO LOAD_PARITY");

fifo_full = 1;

#20;

fifo_full = 0;

#20;

force DUT.low_pkt_valid = 1;

parity_done = 0;

#20;

release DUT.low_pkt_valid;

/////////////////////////////////////////////////////////
// TEST-6
// LOAD_AFTER_FULL -> DECODE_ADDRESS
/////////////////////////////////////////////////////////

$display("\nTEST6 PARITY DONE");

fifo_full = 1;

#20;

fifo_full = 0;

#20;

parity_done = 1;

#20;

parity_done = 0;

/////////////////////////////////////////////////////////
// TEST-7
// Soft Reset
/////////////////////////////////////////////////////////

$display("\nTEST7 SOFT RESET");

soft_rst_0 = 1;

#10;

soft_rst_0 = 0;

#20;

/////////////////////////////////////////////////////////

#100;

$finish;

end

/////////////////////////////////////////////////////////
// Dump
/////////////////////////////////////////////////////////

initial
begin
 $dumpfile("naveen.vcd");
 $dumpvars(0,tb_router_fsm);
end

endmodule

naveen.vcd
$date
	Wed Jun 24 17:50:49 2026
$end
$version
	Icarus Verilog
$end
$timescale
	1ps
$end
$scope module tb_router_fsm $end
$var wire 1 ! write_en_reg $end
$var wire 1 " rst_int_reg $end
$var wire 1 # low_pkt_valid $end
$var wire 1 $ lfd_state $end
$var wire 1 % ld_state $end
$var wire 1 & laf_state $end
$var wire 1 ' full_state $end
$var wire 1 ( detect_add $end
$var wire 1 ) busy $end
$var reg 1 * clk $end
$var reg 2 + data_in [1:0] $end
$var reg 1 , fifo_empty_0 $end
$var reg 1 - fifo_empty_1 $end
$var reg 1 . fifo_empty_2 $end
$var reg 1 / fifo_full $end
$var reg 1 0 parity_done $end
$var reg 1 1 pkt_valid $end
$var reg 1 2 rst_n $end
$var reg 1 3 soft_rst_0 $end
$var reg 1 4 soft_rst_1 $end
$var reg 1 5 soft_rst_2 $end
$scope module DUT $end
$var wire 1 ) busy $end
$var wire 1 * clk $end
$var wire 2 6 data_in [1:0] $end
$var wire 1 , fifo_empty_0 $end
$var wire 1 - fifo_empty_1 $end
$var wire 1 . fifo_empty_2 $end
$var wire 1 / fifo_full $end
$var wire 1 0 parity_done $end
$var wire 1 1 pkt_valid $end
$var wire 1 2 rst_n $end
$var wire 1 3 soft_rst_0 $end
$var wire 1 4 soft_rst_1 $end
$var wire 1 5 soft_rst_2 $end
$var wire 1 ! write_en_reg $end
$var wire 1 " rst_int_reg $end
$var wire 1 # low_pkt_valid $end
$var wire 1 $ lfd_state $end
$var wire 1 % ld_state $end
$var wire 1 & laf_state $end
$var wire 1 ' full_state $end
$var wire 1 ( detect_add $end
$var reg 2 7 addr [1:0] $end
$var reg 3 8 next_state [2:0] $end
$var reg 3 9 state [2:0] $end
$upscope $end
$upscope $end
$enddefinitions $end
#0
$dumpvars
bx 9
b0 8
bx 7
b0 6
05
04
03
02
01
00
0/
1.
1-
1,
b0 +
0*
x)
x(
x'
x&
x%
x$
x#
x"
x!
$end
#5000
0)
0!
1(
0$
0%
0'
0&
0#
0"
b0 9
b0 7
1*
#10000
0*
#15000
1*
#20000
b1 8
0*
11
12
#25000
1)
b10 8
0(
1$
b1 9
1*
#30000
0*
#35000
0)
1!
b10 8
0$
1%
b10 9
1*
#40000
b101 8
0*
01
#45000
1)
b110 8
0%
b101 9
1*
#50000
0*
#55000
0!
b0 8
1"
b110 9
1*
#60000
0*
#65000
0)
1(
0"
b0 9
1*
#70000
b11 8
0*
11
0-
b1 +
b1 6
#75000
1)
0(
b11 9
b11 8
b1 7
1*
#80000
0*
#85000
1*
#90000
b1 8
0*
1-
#95000
1)
b10 8
1$
b1 9
1*
#100000
0*
#105000
0)
1!
b10 8
0$
1%
b10 9
1*
#110000
b101 8
0*
01
#115000
1)
b110 8
0%
b101 9
1*
#120000
0*
#125000
0!
b0 8
1"
b110 9
1*
#130000
0*
11
b10 +
b10 6
#135000
b1 8
0)
1(
0"
b0 9
b10 7
1*
#140000
0*
#145000
1)
b10 8
0(
1$
b1 9
1*
#150000
b10 8
0*
1/
#155000
0)
1!
b100 8
0$
1%
b10 9
1*
#160000
0*
#165000
1)
0!
b100 8
0%
1'
b100 9
1*
#170000
0*
#175000
1*
#180000
b111 8
0*
0/
#185000
1!
b101 8
0'
1&
1#
b111 9
1*
#190000
0*
#195000
1)
1!
b110 8
0&
0#
b101 9
1*
#200000
0*
0#
#205000
0!
b0 8
1"
b110 9
1*
#210000
0*
#215000
b1 8
0)
1(
0"
b0 9
1*
#220000
b1 8
0*
1/
0#
#225000
1)
b10 8
0(
1$
b1 9
1*
#230000
0*
#235000
0)
1!
b100 8
0$
1%
b10 9
1*
#240000
b10 8
0*
0/
#245000
1*
#250000
0*
#255000
1*
#260000
b10 8
0*
1#
#265000
1*
#270000
0*
#275000
1*
#280000
b100 8
0*
1/
0#
#285000
1)
0!
b100 8
0%
1'
b100 9
1*
#290000
0*
#295000
1*
#300000
b111 8
0*
0/
#305000
1!
b101 8
0'
1&
1#
b111 9
1*
#310000
0*
#315000
1)
1!
b110 8
0&
0#
b101 9
1*
#320000
b110 8
0*
10
#325000
0!
b0 8
1"
b110 9
1*
#330000
0*
#335000
b1 8
0)
1(
0"
b0 9
1*
#340000
b1 8
0*
13
00
#345000
1*
#350000
0*
03
#355000
1)
b10 8
0(
1$
b1 9
1*
#360000
0*
#365000
0)
1!
b10 8
0$
1%
b10 9
1*
